loyalty_sdk/__init__.py
loyalty_sdk/client.py
loyalty_sdk/exceptions.py
loyalty_sdk/models.py
loyaltylt_sdk-1.0.3.dist-info/licenses/LICENSE
loyaltylt_sdk-1.0.3.dist-info/METADATA
loyaltylt_sdk-1.0.3.dist-info/WHEEL
loyaltylt_sdk-1.0.3.dist-info/top_level.txt
loyaltylt_sdk-1.0.3.dist-info/RECORD
