Metadata-Version: 2.4
Name: loyaltylt-sdk
Version: 1.0.3
Summary: Official Python SDK for Loyalty.lt Shop API
Home-page: https://github.com/Loyalty-lt/sdk-python
Author: Loyalty.lt
Author-email: developers@loyalty.lt
Project-URL: Bug Tracker, https://github.com/Loyalty-lt/sdk-python/issues
Project-URL: Documentation, https://docs.loyalty.lt/sdk/python
Project-URL: Homepage, https://loyalty.lt
Keywords: loyalty,points,rewards,sdk,api,pos,qr-login
Classifier: Development Status :: 5 - Production/Stable
Classifier: Intended Audience :: Developers
Classifier: License :: OSI Approved :: MIT License
Classifier: Operating System :: OS Independent
Classifier: Programming Language :: Python :: 3
Classifier: Programming Language :: Python :: 3.8
Classifier: Programming Language :: Python :: 3.9
Classifier: Programming Language :: Python :: 3.10
Classifier: Programming Language :: Python :: 3.11
Classifier: Programming Language :: Python :: 3.12
Classifier: Topic :: Software Development :: Libraries :: Python Modules
Requires-Python: >=3.8
License-File: LICENSE
Requires-Dist: requests>=2.28.0
Provides-Extra: dev
Requires-Dist: pytest>=7.0.0; extra == "dev"
Requires-Dist: black>=23.0.0; extra == "dev"
Requires-Dist: flake8>=6.0.0; extra == "dev"
Requires-Dist: mypy>=1.0.0; extra == "dev"
Dynamic: author
Dynamic: author-email
Dynamic: classifier
Dynamic: description
Dynamic: description-content-type
Dynamic: home-page
Dynamic: keywords
Dynamic: license-file
Dynamic: project-url
Dynamic: provides-extra
Dynamic: requires-dist
Dynamic: requires-python
Dynamic: summary
